setup.cfg
setup.py
pyMSAScoring.egg-info/PKG-INFO
pyMSAScoring.egg-info/SOURCES.txt
pyMSAScoring.egg-info/dependency_links.txt
pyMSAScoring.egg-info/top_level.txt
pymsascoring/__init__.py
pymsascoring/score.py
pymsascoring/scoringExample.py
pymsascoring/substitutionmatrix.py
pymsascoring/util.py
pymsascoring/test/__init__.py
pymsascoring/test/test_scoring.py
pymsascoring/test/test_substitutionmatrix.py