Metadata-Version: 1.1
Name: pyMSAScoring
Version: 0.1.2
Summary: Scoring Multiple Sequence Alignments with Python
Home-page: https://github.com/ajnebro/pyMSAScoring
Author: Maria Jose Muñoz, Antonio Benitez, Pablo Rodriguez, Antonio J. Nebro
Author-email: ajnebro@uma.es
License: MIT
Platform: UNKNOWN
Classifier: Development Status :: 3 - Alpha
Classifier: Intended Audience :: Science/Research
Classifier: License :: OSI Approved :: MIT License
Classifier: Topic :: Scientific/Engineering :: Bio-Informatics
Classifier: Programming Language :: Python :: 3.6
